ckanext/__init__.py
ckanext/xloader/__init__.py
ckanext/xloader/action.py
ckanext/xloader/auth.py
ckanext/xloader/cli.py
ckanext/xloader/command.py
ckanext/xloader/config_declaration.yaml
ckanext/xloader/db.py
ckanext/xloader/helpers.py
ckanext/xloader/interfaces.py
ckanext/xloader/job_exceptions.py
ckanext/xloader/jobs.py
ckanext/xloader/loader.py
ckanext/xloader/parser.py
ckanext/xloader/plugin.py
ckanext/xloader/schema.py
ckanext/xloader/utils.py
ckanext/xloader/views.py
ckanext/xloader/templates/datastore/snippets/dictionary_form.html
ckanext/xloader/templates/package/resource_edit_base.html
ckanext/xloader/templates/package/resource_read.html
ckanext/xloader/templates/package/snippets/resource_info.html
ckanext/xloader/templates/package/snippets/resource_item.html
ckanext/xloader/templates/package/snippets/resources.html
ckanext/xloader/templates/xloader/confirm_datastore_delete.html
ckanext/xloader/templates/xloader/resource_data.html
ckanext/xloader/tests/__init__.py
ckanext/xloader/tests/ckan_setup.py
ckanext/xloader/tests/fixtures.py
ckanext/xloader/tests/test_action.py
ckanext/xloader/tests/test_jobs.py
ckanext/xloader/tests/test_loader.py
ckanext/xloader/tests/test_parser.py
ckanext/xloader/tests/test_plugin.py
ckanext/xloader/tests/test_utils.py
ckanext/xloader/webassets/webassets.yml
ckanext/xloader/webassets/css/xloader.css
ckanext_xloader-2.2.0.dist-info/licenses/LICENSE
ckanext_xloader-2.2.0.dist-info/METADATA
ckanext_xloader-2.2.0.dist-info/WHEEL
ckanext_xloader-2.2.0.dist-info/entry_points.txt
ckanext_xloader-2.2.0.dist-info/top_level.txt
ckanext_xloader-2.2.0.dist-info/RECORD
