Metadata-Version: 2.4
Name: ckanext-xloader
Version: 2.2.0
Summary: Express Loader - quickly load data into CKAN DataStore
Author: David Read (davidread), Patricio Del Boca (pdelboca)
Author-email: ThrawnCA <carl.antuar@smartservice.qld.gov.au>, "Jesse Vickery (JVickery-TBS)" <jesse.vickery@tbs-sct.gc.ca>, "Adrià Mercader (amercader)" <amercadero@gmail.com>, "Brett Jones (kowh-ai)" <datashades@linkdigital.com.au>, "William Dutton (duttonw)" <william.dutton@qld.gov.au>
Maintainer: Ian Ward (wardi)
Maintainer-email: "Adrià Mercader (amercader)" <amercadero@gmail.com>, "William Dutton (duttonw)" <william.dutton@qld.gov.au>, "Brett Jones (kowh-ai)" <datashades@linkdigital.com.au>
License: AGPL
Project-URL: Homepage, https://github.com/ckan/ckanext-xloader
Keywords: CKAN,extension,datastore
Classifier: Development Status :: 5 - Production/Stable
Classifier: License :: OSI Approved :: GNU Affero General Public License v3 or later (AGPLv3+)
Classifier: Programming Language :: Python :: 3.7
Classifier: Programming Language :: Python :: 3.8
Classifier: Programming Language :: Python :: 3.9
Classifier: Programming Language :: Python :: 3.10
License-File: LICENSE
Requires-Dist: typing_extensions
Provides-Extra: test
Requires-Dist: pytest-factoryboy; extra == "test"
Dynamic: license-file
